qtma-1.3.0.dist-info/licenses/LICENSE
quantiamagica/__init__.py
quantiamagica/_analysis_impl.py
quantiamagica/adc/__init__.py
quantiamagica/adc/pipeline.py
quantiamagica/adc/sar.py
quantiamagica/adc/sigma_delta.py
quantiamagica/analysis/__init__.py
quantiamagica/core/__init__.py
quantiamagica/core/base.py
quantiamagica/core/events.py
quantiamagica/ide/__init__.py
quantiamagica/ide/server.py
quantiamagica/ide/static/app.js
quantiamagica/ide/static/index.html
quantiamagica/ide/static/style.css
quantiamagica/optim/__init__.py
quantiamagica/optim/adc_optimizer.py
quantiamagica/optim/constraints.py
quantiamagica/optim/gene.py
quantiamagica/optim/gpu_utils.py
quantiamagica/optim/individual.py
quantiamagica/optim/optimizer.py
quantiamagica/optim/population.py
quantiamagica/plotting/__init__.py
quantiamagica/signals/__init__.py
quantiamagica/utils/__init__.py
qtma-1.3.0.dist-info/METADATA
qtma-1.3.0.dist-info/WHEEL
qtma-1.3.0.dist-info/top_level.txt
qtma-1.3.0.dist-info/RECORD
