Metadata-Version: 2.4
Name: qtma
Version: 1.3.0
Summary: ADC Behavioral Event-Driven Simulator with Bukkit-style API
Home-page: https://github.com/KonataLin/QuantiaMagica
Author: KonataLin
Author-email: KonataLin <2424441676@qq.com>
License: MIT
Project-URL: Homepage, https://github.com/KonataLin/QuantiaMagica
Project-URL: Documentation, https://github.com/KonataLin/QuantiaMagica/docs
Project-URL: Repository, https://github.com/KonataLin/QuantiaMagica
Project-URL: Issues, https://github.com/KonataLin/QuantiaMagica/issues
Keywords: adc,analog-to-digital,simulation,sar,pipeline,event-driven
Classifier: Development Status :: 4 - Beta
Classifier: Intended Audience :: Science/Research
Classifier: License :: OSI Approved :: MIT License
Classifier: Programming Language :: Python :: 3
Classifier: Programming Language :: Python :: 3.8
Classifier: Programming Language :: Python :: 3.9
Classifier: Programming Language :: Python :: 3.10
Classifier: Programming Language :: Python :: 3.11
Classifier: Programming Language :: Python :: 3.12
Classifier: Topic :: Scientific/Engineering
Requires-Python: >=3.8
License-File: LICENSE
Requires-Dist: numpy>=1.20.0
Requires-Dist: matplotlib>=3.4.0
Provides-Extra: dev
Requires-Dist: pytest>=7.0.0; extra == "dev"
Requires-Dist: pytest-cov>=4.0.0; extra == "dev"
Requires-Dist: black>=22.0.0; extra == "dev"
Requires-Dist: flake8>=5.0.0; extra == "dev"
Requires-Dist: mypy>=0.990; extra == "dev"
Provides-Extra: docs
Requires-Dist: sphinx>=5.0.0; extra == "docs"
Requires-Dist: sphinx-rtd-theme>=1.0.0; extra == "docs"
Dynamic: author
Dynamic: home-page
Dynamic: license-file
Dynamic: requires-python
